gridpath2/__init__.py
gridpath2/gridpath2.py
gridpath2-0.1.4.dist-info/LICENSE
gridpath2-0.1.4.dist-info/METADATA
gridpath2-0.1.4.dist-info/WHEEL
gridpath2-0.1.4.dist-info/RECORD
