Metadata-Version: 2.1
Name: gridpath2
Version: 0.1.4
Summary: GridPath is a Python library for calculating grid-based paths and intersection points between two coordinates. It's particularly useful for applications requiring precise path tracking on a grid system, such as robotics, game development, or computer graphics.
Home-page: https://github.com/Tomoro0726/gridpath2
License: MIT
Author: Tomoro0726
Classifier: License :: OSI Approved :: MIT License
Classifier: Programming Language :: Python :: 2
Classifier: Programming Language :: Python :: 2.7
Classifier: Programming Language :: Python :: 3
Classifier: Programming Language :: Python :: 3.4
Classifier: Programming Language :: Python :: 3.5
Classifier: Programming Language :: Python :: 3.6
Classifier: Programming Language :: Python :: 3.7
Classifier: Programming Language :: Python :: 3.8
Classifier: Programming Language :: Python :: 3.9
Classifier: Programming Language :: Python :: 3.10
Classifier: Programming Language :: Python :: 3.11
Classifier: Programming Language :: Python :: 3.12
Classifier: Programming Language :: Python :: 3.13
Project-URL: Repository, https://github.com/Tomoro0726/gridpath2
